{
  "title": "Hanukkah 2025",
  "slug": "hanukkah-2025",
  "description": "The festival of lights!",
  "pubDate": "2025-12-15",
  "coverPublicId": "hanukkah-2025/20251215-DSC07249",
  "items": [
    {
      "publicId": "hanukkah-2025/20251214-DSC07230",
      "caption": "20251214-DSC07230"
    },
    {
      "publicId": "hanukkah-2025/20251214-DSC07232",
      "caption": "20251214-DSC07232"
    },
    {
      "publicId": "hanukkah-2025/20251214-DSC07237",
      "caption": "20251214-DSC07237"
    },
    {
      "publicId": "hanukkah-2025/20251214-DSC07243",
      "caption": "20251214-DSC07243"
    },
    {
      "publicId": "hanukkah-2025/20251214-DSC07246",
      "caption": "20251214-DSC07246"
    },
    {
      "publicId": "hanukkah-2025/20251215-DSC07247",
      "caption": "20251215-DSC07247"
    },
    {
      "publicId": "hanukkah-2025/20251215-DSC07249",
      "caption": "20251215-DSC07249"
    },
    {
      "publicId": "hanukkah-2025/20251215-DSC07251",
      "caption": "20251215-DSC07251"
    },
    {
      "publicId": "hanukkah-2025/20251215-DSC07252",
      "caption": "20251215-DSC07252"
    },
    {
      "publicId": "hanukkah-2025/20251215-DSC07257",
      "caption": "20251215-DSC07257"
    },
    {
      "publicId": "hanukkah-2025/20251215-DSC07262",
      "caption": "20251215-DSC07262"
    },
    {
      "publicId": "hanukkah-2025/20251215-DSC07264",
      "caption": "20251215-DSC07264"
    }
  ]
}
